atlassian_jwt/__init__.py
atlassian_jwt/authenticate.py
atlassian_jwt/encode.py
atlassian_jwt/url_utils.py
atlassian_jwt-3.0.0.dist-info/LICENSE.txt
atlassian_jwt-3.0.0.dist-info/METADATA
atlassian_jwt-3.0.0.dist-info/WHEEL
atlassian_jwt-3.0.0.dist-info/top_level.txt
atlassian_jwt-3.0.0.dist-info/RECORD
