Metadata-Version: 2.1
Name: atlassian-jwt
Version: 3.0.0
Summary: JSON web token: pyjwt plus Atlassian query-string-hash claim
Home-page: https://bitbucket.org/atlassian/atlassian-jwt-py
Author: Atlassian
Author-email: bedwards@atlassian.com
License: UNKNOWN
Keywords: jwt,json,web,token,pyjwt,atlassian,connect,addon,query,string,hash,qsh
Platform: UNKNOWN
Classifier: Development Status :: 5 - Production/Stable
Classifier: Intended Audience :: Developers
Classifier: License :: OSI Approved :: MIT License
Classifier: Operating System :: OS Independent
Classifier: Programming Language :: Python
Classifier: Topic :: Software Development :: Libraries :: Python Modules
License-File: LICENSE.txt
Requires-Dist: PyJWT (>=2.2.0)
